<?xml version="1.0" encoding="UTF-8" standalone="yes"?>
<data>
    <pc-stats pClass="0" className="Human Fighter" race="0" str="40" con="43" dex="30" int="21" wit="11" men="25" pAtk="4" pDef="80" mAtk="4" mDef="0" pSpd="300" mSpd="333" acc="33" critical="44" evasion="33" moveSpeed="115" load="81900" x="-71338" y="258271" z="258271" canCraft="false" mColRadius="9.0" mColHeight="23.0" fColRadius="8.0" fColHeight="23.5" items="1147 1146 10 2369 5588" defaulthpbase="80.0" defaulthpadd="11.83" defaulthpmod="0.37" defaultcpbase="32.0" defaultcpadd="4.73" defaultcpmod="0.22" defaultmpbase="30.0" defaultmpadd="5.46" defaultmpmod="0.14" level="1"/>
    <pc-stats pClass="1" className="Warrior" race="0" str="40" con="43" dex="30" int="21" wit="11" men="25" pAtk="4" pDef="80" mAtk="4" mDef="0" pSpd="300" mSpd="333" acc="33" critical="44" evasion="33" moveSpeed="115" load="81900" x="-71338" y="258271" z="258271" canCraft="false" mColRadius="9.0" mColHeight="23.0" fColRadius="8.0" fColHeight="23.5" items="1147 1146 10 2369 5588" defaulthpbase="327.0" defaulthpadd="33.0" defaulthpmod="0.37" defaultcpbase="261.6" defaultcpadd="26.4" defaultcpmod="0.22" defaultmpbase="144.0" defaultmpadd="9.9" defaultmpmod="0.14" level="20"/>
    <pc-stats pClass="2" className="Gladiator" race="0" str="40" con="43" dex="30" int="21" wit="11" men="25" pAtk="4" pDef="80" mAtk="4" mDef="0" pSpd="300" mSpd="333" acc="33" critical="44" evasion="33" moveSpeed="115" load="81900" x="-71338" y="258271" z="258271" canCraft="false" mColRadius="9.0" mColHeight="23.0" fColRadius="8.0" fColHeight="23.5" items="1147 1146 10 2369 5588" defaulthpbase="1044.0" defaulthpadd="49.4" defaulthpmod="0.37" defaultcpbase="939.6" defaultcpadd="44.46" defaultcpmod="0.22" defaultmpbase="359.1" defaultmpadd="19.5" defaultmpmod="0.14" level="40"/>
    <pc-stats pClass="3" className="Warlord" race="0" str="40" con="43" dex="30" int="21" wit="11" men="25" pAtk="4" pDef="80" mAtk="4" mDef="0" pSpd="300" mSpd="333" acc="33" critical="44" evasion="33" moveSpeed="115" load="81900" x="-71338" y="258271" z="258271" canCraft="false" mColRadius="9.0" mColHeight="23.0" fColRadius="8.0" fColHeight="23.5" items="1147 1146 10 2369 5588" defaulthpbase="1044.0" defaulthpadd="54.6" defaulthpmod="0.37" defaultcpbase="835.2" defaultcpadd="43.68" defaultcpmod="0.22" defaultmpbase="359.1" defaultmpadd="19.5" defaultmpmod="0.14" level="40"/>
    <pc-stats pClass="4" className="Human Knight" race="0" str="40" con="43" dex="30" int="21" wit="11" men="25" pAtk="4" pDef="80" mAtk="4" mDef="0" pSpd="300" mSpd="333" acc="33" critical="44" evasion="33" moveSpeed="115" load="81900" x="-71338" y="258271" z="258271" canCraft="false" mColRadius="9.0" mColHeight="23.0" fColRadius="8.0" fColHeight="23.5" items="1147 1146 10 2369 5588" defaulthpbase="327.0" defaulthpadd="29.7" defaulthpmod="0.37" defaultcpbase="196.2" defaultcpadd="17.82" defaultcpmod="0.22" defaultmpbase="144.0" defaultmpadd="9.9" defaultmpmod="0.14" level="20"/>
    <pc-stats pClass="5" className="Paladin" race="0" str="40" con="43" dex="30" int="21" wit="11" men="25" pAtk="4" pDef="80" mAtk="4" mDef="0" pSpd="300" mSpd="333" acc="33" critical="44" evasion="33" moveSpeed="115" load="81900" x="-71338" y="258271" z="258271" canCraft="false" mColRadius="9.0" mColHeight="23.0" fColRadius="8.0" fColHeight="23.5" items="1147 1146 10 2369 5588" defaulthpbase="972.3" defaulthpadd="46.8" defaulthpmod="0.37" defaultcpbase="583.3" defaultcpadd="28.08" defaultcpmod="0.22" defaultmpbase="359.1" defaultmpadd="19.5" defaultmpmod="0.14" level="40"/>
    <pc-stats pClass="6" className="Dark Avenger" race="0" str="40" con="43" dex="30" int="21" wit="11" men="25" pAtk="4" pDef="80" mAtk="4" mDef="0" pSpd="300" mSpd="333" acc="33" critical="44" evasion="33" moveSpeed="115" load="81900" x="-71338" y="258271" z="258271" canCraft="false" mColRadius="9.0" mColHeight="23.0" fColRadius="8.0" fColHeight="23.5" items="1147 1146 10 2369 5588" defaulthpbase="972.3" defaulthpadd="46.8" defaulthpmod="0.37" defaultcpbase="583.3" defaultcpadd="28.08" defaultcpmod="0.22" defaultmpbase="359.1" defaultmpadd="19.5" defaultmpmod="0.14" level="40"/>
    <pc-stats pClass="7" className="Rogue" race="0" str="40" con="43" dex="30" int="21" wit="11" men="25" pAtk="4" pDef="80" mAtk="4" mDef="0" pSpd="300" mSpd="333" acc="33" critical="44" evasion="33" moveSpeed="115" load="81900" x="-71338" y="258271" z="258271" canCraft="false" mColRadius="9.0" mColHeight="23.0" fColRadius="8.0" fColHeight="23.5" items="1147 1146 10 2369 5588" defaulthpbase="327.0" defaulthpadd="27.5" defaulthpmod="0.37" defaultcpbase="130.8" defaultcpadd="11.0" defaultcpmod="0.22" defaultmpbase="144.0" defaultmpadd="9.9" defaultmpmod="0.14" level="20"/>
    <pc-stats pClass="8" className="Treasure Hunter" race="0" str="40" con="43" dex="30" int="21" wit="11" men="25" pAtk="4" pDef="80" mAtk="4" mDef="0" pSpd="300" mSpd="333" acc="33" critical="44" evasion="33" moveSpeed="115" load="81900" x="-71338" y="258271" z="258271" canCraft="false" mColRadius="9.0" mColHeight="23.0" fColRadius="8.0" fColHeight="23.5" items="1147 1146 10 2369 5588" defaulthpbase="924.5" defaulthpadd="41.6" defaulthpmod="0.37" defaultcpbase="369.8" defaultcpadd="16.64" defaultcpmod="0.22" defaultmpbase="359.1" defaultmpadd="19.5" defaultmpmod="0.14" level="40"/>
    <pc-stats pClass="9" className="Hawkeye" race="0" str="40" con="43" dex="30" int="21" wit="11" men="25" pAtk="4" pDef="80" mAtk="4" mDef="0" pSpd="300" mSpd="333" acc="33" critical="44" evasion="33" moveSpeed="115" load="81900" x="-71338" y="258271" z="258271" canCraft="false" mColRadius="9.0" mColHeight="23.0" fColRadius="8.0" fColHeight="23.5" items="1147 1146 10 2369 5588" defaulthpbase="924.5" defaulthpadd="44.2" defaulthpmod="0.37" defaultcpbase="647.1" defaultcpadd="30.94" defaultcpmod="0.22" defaultmpbase="359.1" defaultmpadd="19.5" defaultmpmod="0.14" level="40"/>
    <pc-stats pClass="10" className="Human Mage" race="0" str="22" con="27" dex="21" int="41" wit="20" men="39" pAtk="3" pDef="54" mAtk="3" mDef="0" pSpd="300" mSpd="333" acc="28" critical="40" evasion="28" moveSpeed="120" load="62500" x="-90890" y="248027" z="248027" canCraft="false" mColRadius="7.5" mColHeight="22.8" fColRadius="6.5" fColHeight="22.5" items="425 461 6 5588 0" defaulthpbase="101.0" defaulthpadd="15.57" defaulthpmod="0.37" defaultcpbase="50.5" defaultcpadd="7.84" defaultcpmod="0.22" defaultmpbase="40.0" defaultmpadd="7.38" defaultmpmod="0.14" level="1"/>
    <pc-stats pClass="11" className="Human Wizard" race="0" str="22" con="27" dex="21" int="41" wit="20" men="39" pAtk="3" pDef="54" mAtk="3" mDef="0" pSpd="300" mSpd="333" acc="28" critical="40" evasion="28" moveSpeed="120" load="62500" x="-90890" y="248027" z="248027" canCraft="false" mColRadius="7.5" mColHeight="22.8" fColRadius="6.5" fColHeight="22.5" items="425 461 6 5588 0" defaulthpbase="424.0" defaulthpadd="27.6" defaulthpmod="0.37" defaultcpbase="212.0" defaultcpadd="13.85" defaultcpmod="0.22" defaultmpbase="192.0" defaultmpadd="13.3" defaultmpmod="0.14" level="20"/>
    <pc-stats pClass="12" className="Sorcerer" race="0" str="22" con="27" dex="21" int="41" wit="20" men="39" pAtk="3" pDef="54" mAtk="3" mDef="0" pSpd="300" mSpd="333" acc="28" critical="40" evasion="28" moveSpeed="120" load="62500" x="-90890" y="248027" z="248027" canCraft="false" mColRadius="7.5" mColHeight="22.8" fColRadius="6.5" fColHeight="22.5" items="425 461 6 5588 0" defaulthpbase="1021.5" defaulthpadd="45.6" defaulthpmod="0.37" defaultcpbase="510.7" defaultcpadd="22.85" defaultcpmod="0.22" defaultmpbase="478.8" defaultmpadd="26.1" defaultmpmod="0.14" level="40"/>
    <pc-stats pClass="13" className="Necromancer" race="0" str="22" con="27" dex="21" int="41" wit="20" men="39" pAtk="3" pDef="54" mAtk="3" mDef="0" pSpd="300" mSpd="333" acc="28" critical="40" evasion="28" moveSpeed="120" load="62500" x="-90890" y="248027" z="248027" canCraft="false" mColRadius="7.5" mColHeight="22.8" fColRadius="6.5" fColHeight="22.5" items="425 461 6 5588 0" defaulthpbase="1021.5" defaulthpadd="45.6" defaulthpmod="0.37" defaultcpbase="510.7" defaultcpadd="22.85" defaultcpmod="0.22" defaultmpbase="478.8" defaultmpadd="26.1" defaultmpmod="0.14" level="40"/>
    <pc-stats pClass="14" className="Warlock" race="0" str="22" con="27" dex="21" int="41" wit="20" men="39" pAtk="3" pDef="54" mAtk="3" mDef="0" pSpd="300" mSpd="333" acc="28" critical="40" evasion="28" moveSpeed="120" load="62500" x="-90890" y="248027" z="248027" canCraft="false" mColRadius="7.5" mColHeight="22.8" fColRadius="6.5" fColHeight="22.5" items="425 461 6 5588 0" defaulthpbase="1021.5" defaulthpadd="49.5" defaulthpmod="0.37" defaultcpbase="612.9" defaultcpadd="29.74" defaultcpmod="0.22" defaultmpbase="478.8" defaultmpadd="26.1" defaultmpmod="0.14" level="40"/>
    <pc-stats pClass="15" className="Cleric" race="0" str="22" con="27" dex="21" int="41" wit="20" men="39" pAtk="3" pDef="54" mAtk="3" mDef="0" pSpd="300" mSpd="333" acc="28" critical="40" evasion="28" moveSpeed="120" load="62500" x="-90890" y="248027" z="248027" canCraft="false" mColRadius="7.5" mColHeight="22.8" fColRadius="6.5" fColHeight="22.5" items="425 461 6 5588 0" defaulthpbase="424.0" defaulthpadd="34.2" defaulthpmod="0.37" defaultcpbase="212.0" defaultcpadd="17.15" defaultcpmod="0.22" defaultmpbase="192.0" defaultmpadd="13.3" defaultmpmod="0.14" level="20"/>
    <pc-stats pClass="16" className="Bishop" race="0" str="22" con="27" dex="21" int="41" wit="20" men="39" pAtk="3" pDef="54" mAtk="3" mDef="0" pSpd="300" mSpd="333" acc="28" critical="40" evasion="28" moveSpeed="120" load="62500" x="-90890" y="248027" z="248027" canCraft="false" mColRadius="7.5" mColHeight="22.8" fColRadius="6.5" fColHeight="22.5" items="425 461 6 5588 0" defaulthpbase="1164.9" defaulthpadd="49.5" defaulthpmod="0.37" defaultcpbase="815.4" defaultcpadd="34.68" defaultcpmod="0.22" defaultmpbase="478.8" defaultmpadd="26.1" defaultmpmod="0.14" level="40"/>
    <pc-stats pClass="17" className="Human Prophet" race="0" str="22" con="27" dex="21" int="41" wit="20" men="39" pAtk="3" pDef="54" mAtk="3" mDef="0" pSpd="300" mSpd="333" acc="28" critical="40" evasion="28" moveSpeed="120" load="62500" x="-90890" y="248027" z="248027" canCraft="false" mColRadius="7.5" mColHeight="22.8" fColRadius="6.5" fColHeight="22.5" items="425 461 6 5588 0" defaulthpbase="1164.9" defaulthpadd="53.4" defaulthpmod="0.37" defaultcpbase="582.4" defaultcpadd="26.75" defaultcpmod="0.22" defaultmpbase="478.8" defaultmpadd="26.1" defaultmpmod="0.14" level="40"/>
    <pc-stats pClass="18" className="Elf Fighter" race="1" str="36" con="36" dex="35" int="23" wit="14" men="26" pAtk="4" pDef="80" mAtk="4" mDef="0" pSpd="300" mSpd="333" acc="36" critical="46" evasion="36" moveSpeed="125" load="73000" x="45978" y="41196" z="41196" canCraft="false" mColRadius="7.5" mColHeight="24.0" fColRadius="7.5" fColHeight="23.0" items="1147 1146 10 2369 5588" defaulthpbase="89.0" defaulthpadd="12.74" defaulthpmod="0.37" defaultcpbase="35.6" defaultcpadd="5.0" defaultcpmod="0.22" defaultmpbase="30.0" defaultmpadd="5.46" defaultmpmod="0.14" level="1"/>
    <pc-stats pClass="19" className="Elf Knight" race="1" str="36" con="36" dex="35" int="23" wit="14" men="26" pAtk="4" pDef="80" mAtk="4" mDef="0" pSpd="300" mSpd="333" acc="36" critical="46" evasion="36" moveSpeed="125" load="73000" x="45978" y="41196" z="41196" canCraft="false" mColRadius="7.5" mColHeight="24.0" fColRadius="7.5" fColHeight="23.0" items="1147 1146 10 2369 5588" defaulthpbase="355.0" defaulthpadd="33.0" defaulthpmod="0.37" defaultcpbase="177.5" defaultcpadd="16.5" defaultcpmod="0.22" defaultmpbase="144.0" defaultmpadd="9.9" defaultmpmod="0.14" level="20"/>
    <pc-stats pClass="20" className="Temple Knight" race="1" str="36" con="36" dex="35" int="23" wit="14" men="26" pAtk="4" pDef="80" mAtk="4" mDef="0" pSpd="300" mSpd="333" acc="36" critical="46" evasion="36" moveSpeed="125" load="73000" x="45978" y="41196" z="41196" canCraft="false" mColRadius="7.5" mColHeight="24.0" fColRadius="7.5" fColHeight="23.0" items="1147 1146 10 2369 5588" defaulthpbase="1072.0" defaulthpadd="52.0" defaulthpmod="0.37" defaultcpbase="643.2" defaultcpadd="31.2" defaultcpmod="0.22" defaultmpbase="359.1" defaultmpadd="19.5" defaultmpmod="0.14" level="40"/>
    <pc-stats pClass="21" className="Swordsinger" race="1" str="36" con="36" dex="35" int="23" wit="14" men="26" pAtk="4" pDef="80" mAtk="4" mDef="0" pSpd="300" mSpd="333" acc="36" critical="46" evasion="36" moveSpeed="125" load="73000" x="45978" y="41196" z="41196" canCraft="false" mColRadius="7.5" mColHeight="24.0" fColRadius="7.5" fColHeight="23.0" items="1147 1146 10 2369 5588" defaulthpbase="1072.0" defaulthpadd="54.6" defaulthpmod="0.37" defaultcpbase="536.0" defaultcpadd="27.3" defaultcpmod="0.22" defaultmpbase="359.1" defaultmpadd="19.5" defaultmpmod="0.14" level="40"/>
    <pc-stats pClass="22" className="Scout" race="1" str="36" con="36" dex="35" int="23" wit="14" men="26" pAtk="4" pDef="80" mAtk="4" mDef="0" pSpd="300" mSpd="333" acc="36" critical="46" evasion="36" moveSpeed="125" load="73000" x="45978" y="41196" z="41196" canCraft="false" mColRadius="7.5" mColHeight="24.0" fColRadius="7.5" fColHeight="23.0" items="1147 1146 10 2369 5588" defaulthpbase="355.0" defaulthpadd="30.8" defaulthpmod="0.37" defaultcpbase="142.0" defaultcpadd="12.32" defaultcpmod="0.22" defaultmpbase="144.0" defaultmpadd="9.9" defaultmpmod="0.14" level="20"/>
    <pc-stats pClass="23" className="Plains Walker" race="1" str="36" con="36" dex="35" int="23" wit="14" men="26" pAtk="4" pDef="80" mAtk="4" mDef="0" pSpd="300" mSpd="333" acc="36" critical="46" evasion="36" moveSpeed="125" load="73000" x="45978" y="41196" z="41196" canCraft="false" mColRadius="7.5" mColHeight="24.0" fColRadius="7.5" fColHeight="23.0" items="1147 1146 10 2369 5588" defaulthpbase="1024.2" defaulthpadd="46.8" defaulthpmod="0.37" defaultcpbase="409.6" defaultcpadd="18.72" defaultcpmod="0.22" defaultmpbase="359.1" defaultmpadd="19.5" defaultmpmod="0.14" level="40"/>
    <pc-stats pClass="24" className="Silver Ranger" race="1" str="36" con="36" dex="35" int="23" wit="14" men="26" pAtk="4" pDef="80" mAtk="4" mDef="0" pSpd="300" mSpd="333" acc="36" critical="46" evasion="36" moveSpeed="125" load="73000" x="45978" y="41196" z="41196" canCraft="false" mColRadius="7.5" mColHeight="24.0" fColRadius="7.5" fColHeight="23.0" items="1147 1146 10 2369 5588" defaulthpbase="1024.2" defaulthpadd="49.4" defaulthpmod="0.37" defaultcpbase="512.1" defaultcpadd="24.7" defaultcpmod="0.22" defaultmpbase="359.1" defaultmpadd="19.5" defaultmpmod="0.14" level="40"/>
    <pc-stats pClass="25" className="Elf Mage" race="1" str="21" con="25" dex="24" int="37" wit="23" men="40" pAtk="3" pDef="54" mAtk="3" mDef="0" pSpd="300" mSpd="333" acc="30" critical="41" evasion="30" moveSpeed="122" load="62400" x="46182" y="41198" z="41198" canCraft="false" mColRadius="7.5" mColHeight="24.0" fColRadius="7.5" fColHeight="23.0" items="425 461 6 5588 0" defaulthpbase="104.0" defaulthpadd="15.57" defaulthpmod="0.37" defaultcpbase="52.0" defaultcpadd="7.84" defaultcpmod="0.22" defaultmpbase="40.0" defaultmpadd="7.38" defaultmpmod="0.14" level="1"/>
    <pc-stats pClass="26" className="Elf Wizard" race="1" str="21" con="25" dex="24" int="37" wit="23" men="40" pAtk="3" pDef="54" mAtk="3" mDef="0" pSpd="300" mSpd="333" acc="30" critical="41" evasion="30" moveSpeed="122" load="62400" x="46182" y="41198" z="41198" canCraft="false" mColRadius="7.5" mColHeight="24.0" fColRadius="7.5" fColHeight="23.0" items="425 461 6 5588 0" defaulthpbase="427.0" defaulthpadd="28.7" defaulthpmod="0.37" defaultcpbase="213.5" defaultcpadd="14.4" defaultcpmod="0.22" defaultmpbase="192.0" defaultmpadd="13.3" defaultmpmod="0.14" level="20"/>
    <pc-stats pClass="27" className="Spellsinger" race="1" str="21" con="25" dex="24" int="37" wit="23" men="40" pAtk="3" pDef="54" mAtk="3" mDef="0" pSpd="300" mSpd="333" acc="30" critical="41" evasion="30" moveSpeed="122" load="62400" x="46182" y="41198" z="41198" canCraft="false" mColRadius="7.5" mColHeight="24.0" fColRadius="7.5" fColHeight="23.0" items="425 461 6 5588 0" defaulthpbase="1048.4" defaulthpadd="48.2" defaulthpmod="0.37" defaultcpbase="524.2" defaultcpadd="24.15" defaultcpmod="0.22" defaultmpbase="478.8" defaultmpadd="26.1" defaultmpmod="0.14" level="40"/>
    <pc-stats pClass="28" className="Elemental Summoner" race="1" str="21" con="25" dex="24" int="37" wit="23" men="40" pAtk="3" pDef="54" mAtk="3" mDef="0" pSpd="300" mSpd="333" acc="30" critical="41" evasion="30" moveSpeed="122" load="62400" x="46182" y="41198" z="41198" canCraft="false" mColRadius="7.5" mColHeight="24.0" fColRadius="7.5" fColHeight="23.0" items="425 461 6 5588 0" defaulthpbase="1048.4" defaulthpadd="50.8" defaulthpmod="0.37" defaultcpbase="629.0" defaultcpadd="30.52" defaultcpmod="0.22" defaultmpbase="478.8" defaultmpadd="26.1" defaultmpmod="0.14" level="40"/>
    <pc-stats pClass="29" className="Oracle" race="1" str="21" con="25" dex="24" int="37" wit="23" men="40" pAtk="3" pDef="54" mAtk="3" mDef="0" pSpd="300" mSpd="333" acc="30" critical="41" evasion="30" moveSpeed="122" load="62400" x="46182" y="41198" z="41198" canCraft="false" mColRadius="7.5" mColHeight="24.0" fColRadius="7.5" fColHeight="23.0" items="425 461 6 5588 0" defaulthpbase="427.0" defaulthpadd="35.3" defaulthpmod="0.37" defaultcpbase="213.5" defaultcpadd="17.7" defaultcpmod="0.22" defaultmpbase="192.0" defaultmpadd="13.3" defaultmpmod="0.14" level="20"/>
    <pc-stats pClass="30" className="Elder" race="1" str="21" con="25" dex="24" int="37" wit="23" men="40" pAtk="3" pDef="54" mAtk="3" mDef="0" pSpd="300" mSpd="333" acc="30" critical="41" evasion="30" moveSpeed="122" load="62400" x="46182" y="41198" z="41198" canCraft="false" mColRadius="7.5" mColHeight="24.0" fColRadius="7.5" fColHeight="23.0" items="425 461 6 5588 0" defaulthpbase="1191.8" defaulthpadd="54.7" defaulthpmod="0.37" defaultcpbase="595.9" defaultcpadd="27.4" defaultcpmod="0.22" defaultmpbase="478.8" defaultmpadd="26.1" defaultmpmod="0.14" level="40"/>
    <pc-stats pClass="31" className="DE Fighter" race="2" str="41" con="32" dex="34" int="25" wit="12" men="26" pAtk="4" pDef="80" mAtk="4" mDef="0" pSpd="300" mSpd="333" acc="35" critical="45" evasion="35" moveSpeed="122" load="69000" x="28377" y="10916" z="10916" canCraft="false" mColRadius="7.5" mColHeight="24.0" fColRadius="7.0" fColHeight="23.5" items="1147 1146 10 2369 5588" defaulthpbase="94.0" defaulthpadd="13.65" defaulthpmod="0.37" defaultcpbase="37.6" defaultcpadd="5.46" defaultcpmod="0.22" defaultmpbase="30.0" defaultmpadd="5.46" defaultmpmod="0.14" level="1"/>
    <pc-stats pClass="32" className="Palus Knight" race="2" str="41" con="32" dex="34" int="25" wit="12" men="26" pAtk="4" pDef="80" mAtk="4" mDef="0" pSpd="300" mSpd="333" acc="35" critical="45" evasion="35" moveSpeed="122" load="69000" x="28377" y="10916" z="10916" canCraft="false" mColRadius="7.5" mColHeight="24.0" fColRadius="7.0" fColHeight="23.5" items="1147 1146 10 2369 5588" defaulthpbase="379.0" defaulthpadd="35.2" defaulthpmod="0.37" defaultcpbase="189.5" defaultcpadd="17.6" defaultcpmod="0.22" defaultmpbase="144.0" defaultmpadd="9.9" defaultmpmod="0.14" level="20"/>
    <pc-stats pClass="33" className="Shillien Knight" race="2" str="41" con="32" dex="34" int="25" wit="12" men="26" pAtk="4" pDef="80" mAtk="4" mDef="0" pSpd="300" mSpd="333" acc="35" critical="45" evasion="35" moveSpeed="122" load="69000" x="28377" y="10916" z="10916" canCraft="false" mColRadius="7.5" mColHeight="24.0" fColRadius="7.0" fColHeight="23.5" items="1147 1146 10 2369 5588" defaulthpbase="1143.8" defaulthpadd="54.6" defaulthpmod="0.37" defaultcpbase="686.2" defaultcpadd="32.76" defaultcpmod="0.22" defaultmpbase="359.1" defaultmpadd="19.5" defaultmpmod="0.14" level="40"/>
    <pc-stats pClass="34" className="Bladedancer" race="2" str="41" con="32" dex="34" int="25" wit="12" men="26" pAtk="4" pDef="80" mAtk="4" mDef="0" pSpd="300" mSpd="333" acc="35" critical="45" evasion="35" moveSpeed="122" load="69000" x="28377" y="10916" z="10916" canCraft="false" mColRadius="7.5" mColHeight="24.0" fColRadius="7.0" fColHeight="23.5" items="1147 1146 10 2369 5588" defaulthpbase="1143.8" defaulthpadd="58.5" defaulthpmod="0.37" defaultcpbase="571.9" defaultcpadd="29.25" defaultcpmod="0.22" defaultmpbase="359.1" defaultmpadd="19.5" defaultmpmod="0.14" level="40"/>
    <pc-stats pClass="35" className="Assassin" race="2" str="41" con="32" dex="34" int="25" wit="12" men="26" pAtk="4" pDef="80" mAtk="4" mDef="0" pSpd="300" mSpd="333" acc="35" critical="45" evasion="35" moveSpeed="122" load="69000" x="28377" y="10916" z="10916" canCraft="false" mColRadius="7.5" mColHeight="24.0" fColRadius="7.0" fColHeight="23.5" items="1147 1146 10 2369 5588" defaulthpbase="379.0" defaulthpadd="33.0" defaulthpmod="0.37" defaultcpbase="151.6" defaultcpadd="13.2" defaultcpmod="0.22" defaultmpbase="144.0" defaultmpadd="9.9" defaultmpmod="0.14" level="20"/>
    <pc-stats pClass="36" className="Abyss Walker" race="2" str="41" con="32" dex="34" int="25" wit="12" men="26" pAtk="4" pDef="80" mAtk="4" mDef="0" pSpd="300" mSpd="333" acc="35" critical="45" evasion="35" moveSpeed="122" load="69000" x="28377" y="10916" z="10916" canCraft="false" mColRadius="7.5" mColHeight="24.0" fColRadius="7.0" fColHeight="23.5" items="1147 1146 10 2369 5588" defaulthpbase="1096.0" defaulthpadd="49.4" defaulthpmod="0.37" defaultcpbase="438.4" defaultcpadd="19.76" defaultcpmod="0.22" defaultmpbase="359.1" defaultmpadd="19.5" defaultmpmod="0.14" level="40"/>
    <pc-stats pClass="37" className="Phantom Ranger" race="2" str="41" con="32" dex="34" int="25" wit="12" men="26" pAtk="4" pDef="80" mAtk="4" mDef="0" pSpd="300" mSpd="333" acc="35" critical="45" evasion="35" moveSpeed="122" load="69000" x="28377" y="10916" z="10916" canCraft="false" mColRadius="7.5" mColHeight="24.0" fColRadius="7.0" fColHeight="23.5" items="1147 1146 10 2369 5588" defaulthpbase="1096.0" defaulthpadd="52.0" defaulthpmod="0.37" defaultcpbase="548.0" defaultcpadd="26.0" defaultcpmod="0.22" defaultmpbase="359.1" defaultmpadd="19.5" defaultmpmod="0.14" level="40"/>
    <pc-stats pClass="38" className="DE Mage" race="2" str="23" con="24" dex="23" int="44" wit="19" men="37" pAtk="3" pDef="54" mAtk="3" mDef="0" pSpd="300" mSpd="333" acc="29" critical="41" evasion="29" moveSpeed="122" load="61000" x="28295" y="11063" z="11063" canCraft="false" mColRadius="7.5" mColHeight="24.0" fColRadius="7.0" fColHeight="23.5" items="425 461 6 5588 0" defaulthpbase="106.0" defaulthpadd="15.57" defaulthpmod="0.37" defaultcpbase="53.0" defaultcpadd="7.84" defaultcpmod="0.22" defaultmpbase="40.0" defaultmpadd="7.38" defaultmpmod="0.14" level="1"/>
    <pc-stats pClass="39" className="DE Wizard" race="2" str="23" con="24" dex="23" int="44" wit="19" men="37" pAtk="3" pDef="54" mAtk="3" mDef="0" pSpd="300" mSpd="333" acc="29" critical="41" evasion="29" moveSpeed="122" load="61000" x="28295" y="11063" z="11063" canCraft="false" mColRadius="7.5" mColHeight="24.0" fColRadius="7.0" fColHeight="23.5" items="425 461 6 5588 0" defaulthpbase="429.0" defaulthpadd="29.8" defaulthpmod="0.37" defaultcpbase="214.5" defaultcpadd="14.95" defaultcpmod="0.22" defaultmpbase="192.0" defaultmpadd="13.3" defaultmpmod="0.14" level="20"/>
    <pc-stats pClass="40" className="Spell Howler" race="2" str="23" con="24" dex="23" int="44" wit="19" men="37" pAtk="3" pDef="54" mAtk="3" mDef="0" pSpd="300" mSpd="333" acc="29" critical="41" evasion="29" moveSpeed="122" load="61000" x="28295" y="11063" z="11063" canCraft="false" mColRadius="7.5" mColHeight="24.0" fColRadius="7.0" fColHeight="23.5" items="425 461 6 5588 0" defaulthpbase="1074.3" defaulthpadd="48.2" defaulthpmod="0.37" defaultcpbase="537.1" defaultcpadd="24.15" defaultcpmod="0.22" defaultmpbase="478.8" defaultmpadd="26.1" defaultmpmod="0.14" level="40"/>
    <pc-stats pClass="41" className="Phantom Summoner" race="2" str="23" con="24" dex="23" int="44" wit="19" men="37" pAtk="3" pDef="54" mAtk="3" mDef="0" pSpd="300" mSpd="333" acc="29" critical="41" evasion="29" moveSpeed="122" load="61000" x="28295" y="11063" z="11063" canCraft="false" mColRadius="7.5" mColHeight="24.0" fColRadius="7.0" fColHeight="23.5" items="425 461 6 5588 0" defaulthpbase="1074.3" defaulthpadd="52.1" defaulthpmod="0.37" defaultcpbase="644.5" defaultcpadd="31.3" defaultcpmod="0.22" defaultmpbase="478.8" defaultmpadd="26.1" defaultmpmod="0.14" level="40"/>
    <pc-stats pClass="42" className="Shillien Oracle" race="2" str="23" con="24" dex="23" int="44" wit="19" men="37" pAtk="3" pDef="54" mAtk="3" mDef="0" pSpd="300" mSpd="333" acc="29" critical="41" evasion="29" moveSpeed="122" load="61000" x="28295" y="11063" z="11063" canCraft="false" mColRadius="7.5" mColHeight="24.0" fColRadius="7.0" fColHeight="23.5" items="425 461 6 5588 0" defaulthpbase="429.0" defaulthpadd="36.4" defaulthpmod="0.37" defaultcpbase="214.5" defaultcpadd="18.25" defaultcpmod="0.22" defaultmpbase="192.0" defaultmpadd="13.3" defaultmpmod="0.14" level="20"/>
    <pc-stats pClass="43" className="Shillien Elder" race="2" str="23" con="24" dex="23" int="44" wit="19" men="37" pAtk="3" pDef="54" mAtk="3" mDef="0" pSpd="300" mSpd="333" acc="29" critical="41" evasion="29" moveSpeed="122" load="61000" x="28295" y="11063" z="11063" canCraft="false" mColRadius="7.5" mColHeight="24.0" fColRadius="7.0" fColHeight="23.5" items="425 461 6 5588 0" defaulthpbase="1217.7" defaulthpadd="54.7" defaulthpmod="0.37" defaultcpbase="608.8" defaultcpadd="27.4" defaultcpmod="0.22" defaultmpbase="478.8" defaultmpadd="26.1" defaultmpmod="0.14" level="40"/>
    <pc-stats pClass="44" className="Orc Fighter" race="3" str="40" con="47" dex="26" int="18" wit="12" men="27" pAtk="4" pDef="80" mAtk="4" mDef="0" pSpd="300" mSpd="333" acc="31" critical="42" evasion="31" moveSpeed="117" load="87000" x="-56693" y="-113610" z="-113610" canCraft="false" mColRadius="11.0" mColHeight="28.0" fColRadius="7.0" fColHeight="27.0" items="1147 1146 2368 2369 5588" defaulthpbase="80.0" defaulthpadd="12.64" defaulthpmod="0.37" defaultcpbase="40.0" defaultcpadd="6.27" defaultcpmod="0.22" defaultmpbase="30.0" defaultmpadd="5.36" defaultmpmod="0.14" level="1"/>
    <pc-stats pClass="45" className="Raider" race="3" str="40" con="47" dex="26" int="18" wit="12" men="27" pAtk="4" pDef="80" mAtk="4" mDef="0" pSpd="300" mSpd="333" acc="31" critical="42" evasion="31" moveSpeed="117" load="87000" x="-56693" y="-113610" z="-113610" canCraft="false" mColRadius="11.0" mColHeight="28.0" fColRadius="7.0" fColHeight="27.0" items="1147 1146 2368 2369 5588" defaulthpbase="346.0" defaulthpadd="35.1" defaulthpmod="0.37" defaultcpbase="242.2" defaultcpadd="24.54" defaultcpmod="0.22" defaultmpbase="144.0" defaultmpadd="9.8" defaultmpmod="0.14" level="20"/>
    <pc-stats pClass="46" className="Destroyer" race="3" str="40" con="47" dex="26" int="18" wit="12" men="27" pAtk="4" pDef="80" mAtk="4" mDef="0" pSpd="300" mSpd="333" acc="31" critical="42" evasion="31" moveSpeed="117" load="87000" x="-56693" y="-113610" z="-113610" canCraft="false" mColRadius="11.0" mColHeight="28.0" fColRadius="7.0" fColHeight="27.0" items="1147 1146 2368 2369 5588" defaulthpbase="1110.8" defaulthpadd="57.1" defaulthpmod="0.37" defaultcpbase="777.5" defaultcpadd="39.94" defaultcpmod="0.22" defaultmpbase="359.1" defaultmpadd="19.4" defaultmpmod="0.14" level="40"/>
    <pc-stats pClass="47" className="Monk" race="3" str="40" con="47" dex="26" int="18" wit="12" men="27" pAtk="4" pDef="80" mAtk="4" mDef="0" pSpd="300" mSpd="333" acc="31" critical="42" evasion="31" moveSpeed="117" load="87000" x="-56682" y="-113610" z="-113610" canCraft="false" mColRadius="11.0" mColHeight="28.0" fColRadius="7.0" fColHeight="27.0" items="1147 1146 2368 2369 5588" defaulthpbase="346.0" defaulthpadd="32.9" defaulthpmod="0.37" defaultcpbase="173.0" defaultcpadd="16.4" defaultcpmod="0.22" defaultmpbase="144.0" defaultmpadd="9.8" defaultmpmod="0.14" level="20"/>
    <pc-stats pClass="48" className="Tyrant" race="3" str="40" con="47" dex="26" int="18" wit="12" men="27" pAtk="4" pDef="80" mAtk="4" mDef="0" pSpd="300" mSpd="333" acc="31" critical="42" evasion="31" moveSpeed="117" load="87000" x="-56693" y="-113610" z="-113610" canCraft="false" mColRadius="11.0" mColHeight="28.0" fColRadius="7.0" fColHeight="27.0" items="1147 1146 2368 2369 5588" defaulthpbase="1063.0" defaulthpadd="54.5" defaulthpmod="0.37" defaultcpbase="531.5" defaultcpadd="27.2" defaultcpmod="0.22" defaultmpbase="359.1" defaultmpadd="19.4" defaultmpmod="0.14" level="40"/>
    <pc-stats pClass="49" className="Orc Mage" race="3" str="27" con="31" dex="24" int="31" wit="15" men="42" pAtk="3" pDef="54" mAtk="3" mDef="0" pSpd="300" mSpd="333" acc="30" critical="41" evasion="30" moveSpeed="121" load="68000" x="-56682" y="-113730" z="-113730" canCraft="false" mColRadius="7.0" mColHeight="27.5" fColRadius="8.0" fColHeight="25.5" items="425 461 2368 5588 0" defaulthpbase="95.0" defaulthpadd="15.47" defaulthpmod="0.37" defaultcpbase="47.5" defaultcpadd="7.74" defaultcpmod="0.22" defaultmpbase="40.0" defaultmpadd="7.28" defaultmpmod="0.14" level="1"/>
    <pc-stats pClass="50" className="Shaman" race="3" str="27" con="31" dex="24" int="31" wit="15" men="42" pAtk="3" pDef="54" mAtk="3" mDef="0" pSpd="300" mSpd="333" acc="30" critical="41" evasion="30" moveSpeed="121" load="68000" x="-56682" y="-113730" z="-113730" canCraft="false" mColRadius="7.0" mColHeight="27.5" fColRadius="8.0" fColHeight="25.5" items="425 461 2368 5588 0" defaulthpbase="418.0" defaulthpadd="35.2" defaulthpmod="0.37" defaultcpbase="209.0" defaultcpadd="17.6" defaultcpmod="0.22" defaultmpbase="192.0" defaultmpadd="13.2" defaultmpmod="0.14" level="20"/>
    <pc-stats pClass="51" className="Overlord" race="3" str="27" con="31" dex="24" int="31" wit="15" men="42" pAtk="3" pDef="54" mAtk="3" mDef="0" pSpd="300" mSpd="333" acc="30" critical="41" evasion="30" moveSpeed="121" load="68000" x="-56682" y="-113730" z="-113730" canCraft="false" mColRadius="7.0" mColHeight="27.5" fColRadius="8.0" fColHeight="25.5" items="425 461 2368 5588 0" defaulthpbase="1182.8" defaulthpadd="53.3" defaulthpmod="0.37" defaultcpbase="946.2" defaultcpadd="42.64" defaultcpmod="0.22" defaultmpbase="478.8" defaultmpadd="26.0" defaultmpmod="0.14" level="40"/>
    <pc-stats pClass="52" className="Warcryer" race="3" str="27" con="31" dex="24" int="31" wit="15" men="42" pAtk="3" pDef="54" mAtk="3" mDef="0" pSpd="300" mSpd="333" acc="30" critical="41" evasion="30" moveSpeed="121" load="68000" x="-56682" y="-113730" z="-113730" canCraft="false" mColRadius="7.0" mColHeight="27.5" fColRadius="8.0" fColHeight="25.5" items="425 461 2368 5588 0" defaulthpbase="1182.8" defaulthpadd="53.3" defaulthpmod="0.37" defaultcpbase="591.4" defaultcpadd="26.65" defaultcpmod="0.22" defaultmpbase="478.8" defaultmpadd="26.0" defaultmpmod="0.14" level="40"/>
    <pc-stats pClass="53" className="Dwarf Fighter" race="4" str="39" con="45" dex="29" int="20" wit="10" men="27" pAtk="4" pDef="80" mAtk="4" mDef="0" pSpd="300" mSpd="333" acc="33" critical="43" evasion="33" moveSpeed="115" load="83000" x="108512" y="-174026" z="-174026" canCraft="true" mColRadius="9.0" mColHeight="18.0" fColRadius="5.0" fColHeight="19.0" items="1147 1146 10 2370 5588" defaulthpbase="80.0" defaulthpadd="12.64" defaulthpmod="0.37" defaultcpbase="56.0" defaultcpadd="8.82" defaultcpmod="0.22" defaultmpbase="30.0" defaultmpadd="5.36" defaultmpmod="0.14" level="1"/>
    <pc-stats pClass="54" className="Scavenger" race="4" str="39" con="45" dex="29" int="20" wit="10" men="27" pAtk="4" pDef="80" mAtk="4" mDef="0" pSpd="300" mSpd="333" acc="33" critical="43" evasion="33" moveSpeed="115" load="83000" x="108512" y="-174026" z="-174026" canCraft="true" mColRadius="9.0" mColHeight="18.0" fColRadius="5.0" fColHeight="19.0" items="1147 1146 10 2370 5588" defaulthpbase="346.0" defaulthpadd="35.1" defaulthpmod="0.37" defaultcpbase="242.2" defaultcpadd="24.54" defaultcpmod="0.22" defaultmpbase="144.0" defaultmpadd="9.8" defaultmpmod="0.14" level="20"/>
    <pc-stats pClass="55" className="Bounty Hunter" race="4" str="39" con="45" dex="29" int="20" wit="10" men="27" pAtk="4" pDef="80" mAtk="4" mDef="0" pSpd="300" mSpd="333" acc="33" critical="43" evasion="33" moveSpeed="115" load="83000" x="108512" y="-174026" z="-174026" canCraft="true" mColRadius="9.0" mColHeight="18.0" fColRadius="5.0" fColHeight="19.0" items="1147 1146 10 2370 5588" defaulthpbase="1110.8" defaulthpadd="57.1" defaulthpmod="0.37" defaultcpbase="777.5" defaultcpadd="39.94" defaultcpmod="0.22" defaultmpbase="359.1" defaultmpadd="19.4" defaultmpmod="0.14" level="40"/>
    <pc-stats pClass="56" className="Artisan" race="4" str="39" con="45" dex="29" int="20" wit="10" men="27" pAtk="4" pDef="80" mAtk="4" mDef="0" pSpd="300" mSpd="333" acc="33" critical="43" evasion="33" moveSpeed="115" load="83000" x="108512" y="-174026" z="-174026" canCraft="true" mColRadius="9.0" mColHeight="18.0" fColRadius="5.0" fColHeight="19.0" items="1147 1146 10 2370 5588" defaulthpbase="346.0" defaulthpadd="32.9" defaulthpmod="0.37" defaultcpbase="276.8" defaultcpadd="26.3" defaultcpmod="0.22" defaultmpbase="144.0" defaultmpadd="9.8" defaultmpmod="0.14" level="20"/>
    <pc-stats pClass="57" className="Warsmith" race="4" str="39" con="45" dex="29" int="20" wit="10" men="27" pAtk="4" pDef="80" mAtk="4" mDef="0" pSpd="300" mSpd="333" acc="33" critical="43" evasion="33" moveSpeed="115" load="83000" x="108512" y="-174026" z="-174026" canCraft="true" mColRadius="9.0" mColHeight="18.0" fColRadius="5.0" fColHeight="19.0" items="1147 1146 10 2370 5588" defaulthpbase="1063.0" defaulthpadd="54.5" defaulthpmod="0.37" defaultcpbase="850.4" defaultcpadd="43.58" defaultcpmod="0.22" defaultmpbase="359.1" defaultmpadd="19.4" defaultmpmod="0.14" level="40"/>
    <pc-stats pClass="88" className="Duelist" race="0" str="40" con="43" dex="30" int="21" wit="11" men="25" pAtk="4" pDef="80" mAtk="4" mDef="0" pSpd="300" mSpd="333" acc="33" critical="44" evasion="33" moveSpeed="115" load="81900" x="-71338" y="258271" z="258271" canCraft="false" mColRadius="9.0" mColHeight="23.0" fColRadius="8.0" fColHeight="23.5" items="1147 1146 10 2369 5588" defaulthpbase="3061.8" defaulthpadd="63.08" defaulthpmod="0.37" defaultcpbase="2755.6" defaultcpadd="56.77" defaultcpmod="0.22" defaultmpbase="1155.6" defaultmpadd="24.9" defaultmpmod="0.14" level="76"/>
    <pc-stats pClass="89" className="DreadNought" race="0" str="40" con="43" dex="30" int="21" wit="11" men="25" pAtk="4" pDef="80" mAtk="4" mDef="0" pSpd="300" mSpd="333" acc="33" critical="44" evasion="33" moveSpeed="115" load="81900" x="-71338" y="258271" z="258271" canCraft="false" mColRadius="9.0" mColHeight="23.0" fColRadius="8.0" fColHeight="23.5" items="1147 1146 10 2369 5588" defaulthpbase="3274.2" defaulthpadd="69.72" defaulthpmod="0.37" defaultcpbase="2619.3" defaultcpadd="55.78" defaultcpmod="0.22" defaultmpbase="1155.6" defaultmpadd="24.9" defaultmpmod="0.14" level="76"/>
    <pc-stats pClass="90" className="Phoenix Knight" race="0" str="40" con="43" dex="30" int="21" wit="11" men="25" pAtk="4" pDef="80" mAtk="4" mDef="0" pSpd="300" mSpd="333" acc="33" critical="44" evasion="33" moveSpeed="115" load="81900" x="-71338" y="258271" z="258271" canCraft="false" mColRadius="9.0" mColHeight="23.0" fColRadius="8.0" fColHeight="23.5" items="1147 1146 10 2369 5588" defaulthpbase="2883.9" defaulthpadd="59.76" defaulthpmod="0.37" defaultcpbase="1730.3" defaultcpadd="35.86" defaultcpmod="0.22" defaultmpbase="1155.6" defaultmpadd="24.9" defaultmpmod="0.14" level="76"/>
    <pc-stats pClass="91" className="Hell Knight" race="0" str="40" con="43" dex="30" int="21" wit="11" men="25" pAtk="4" pDef="80" mAtk="4" mDef="0" pSpd="300" mSpd="333" acc="33" critical="44" evasion="33" moveSpeed="115" load="81900" x="-71338" y="258271" z="258271" canCraft="false" mColRadius="9.0" mColHeight="23.0" fColRadius="8.0" fColHeight="23.5" items="1147 1146 10 2369 5588" defaulthpbase="2883.9" defaulthpadd="59.76" defaulthpmod="0.37" defaultcpbase="1730.3" defaultcpadd="35.86" defaultcpmod="0.22" defaultmpbase="1155.6" defaultmpadd="24.9" defaultmpmod="0.14" level="76"/>
    <pc-stats pClass="92" className="Sagittarius" race="0" str="40" con="43" dex="30" int="21" wit="11" men="25" pAtk="4" pDef="80" mAtk="4" mDef="0" pSpd="300" mSpd="333" acc="33" critical="44" evasion="33" moveSpeed="115" load="81900" x="-71338" y="258271" z="258271" canCraft="false" mColRadius="9.0" mColHeight="23.0" fColRadius="8.0" fColHeight="23.5" items="1147 1146 10 2369 5588" defaulthpbase="2729.9" defaulthpadd="56.44" defaulthpmod="0.37" defaultcpbase="1910.9" defaultcpadd="39.51" defaultcpmod="0.22" defaultmpbase="1155.6" defaultmpadd="24.9" defaultmpmod="0.14" level="76"/>
    <pc-stats pClass="93" className="Adventurer" race="0" str="40" con="43" dex="30" int="21" wit="11" men="25" pAtk="4" pDef="80" mAtk="4" mDef="0" pSpd="300" mSpd="333" acc="33" critical="44" evasion="33" moveSpeed="115" load="81900" x="-71338" y="258271" z="258271" canCraft="false" mColRadius="9.0" mColHeight="23.0" fColRadius="8.0" fColHeight="23.5" items="1147 1146 10 2369 5588" defaulthpbase="2623.7" defaulthpadd="53.12" defaulthpmod="0.37" defaultcpbase="1049.4" defaultcpadd="21.25" defaultcpmod="0.22" defaultmpbase="1155.6" defaultmpadd="24.9" defaultmpmod="0.14" level="76"/>
    <pc-stats pClass="94" className="Archmage" race="0" str="22" con="27" dex="21" int="41" wit="20" men="39" pAtk="3" pDef="54" mAtk="3" mDef="0" pSpd="300" mSpd="333" acc="28" critical="40" evasion="28" moveSpeed="120" load="62500" x="-90890" y="248027" z="248027" canCraft="false" mColRadius="7.5" mColHeight="22.8" fColRadius="6.5" fColHeight="22.5" items="425 461 6 5588 0" defaulthpbase="2880.0" defaulthpadd="58.1" defaulthpmod="0.37" defaultcpbase="1440.0" defaultcpadd="29.05" defaultcpmod="0.22" defaultmpbase="1540.8" defaultmpadd="33.2" defaultmpmod="0.14" level="76"/>
    <pc-stats pClass="95" className="Soultaker" race="0" str="22" con="27" dex="21" int="41" wit="20" men="39" pAtk="3" pDef="54" mAtk="3" mDef="0" pSpd="300" mSpd="333" acc="28" critical="40" evasion="28" moveSpeed="120" load="62500" x="-90890" y="248027" z="248027" canCraft="false" mColRadius="7.5" mColHeight="22.8" fColRadius="6.5" fColHeight="22.5" items="425 461 6 5588 0" defaulthpbase="2880.0" defaulthpadd="58.1" defaulthpmod="0.37" defaultcpbase="1440.0" defaultcpadd="29.05" defaultcpmod="0.22" defaultmpbase="1540.8" defaultmpadd="33.2" defaultmpmod="0.14" level="76"/>
    <pc-stats pClass="96" className="Arcana Lord" race="0" str="22" con="27" dex="21" int="41" wit="20" men="39" pAtk="3" pDef="54" mAtk="3" mDef="0" pSpd="300" mSpd="333" acc="28" critical="40" evasion="28" moveSpeed="120" load="62500" x="-90890" y="248027" z="248027" canCraft="false" mColRadius="7.5" mColHeight="22.8" fColRadius="6.5" fColHeight="22.5" items="425 461 6 5588 0" defaulthpbase="3039.3" defaulthpadd="63.08" defaulthpmod="0.37" defaultcpbase="1823.5" defaultcpadd="37.85" defaultcpmod="0.22" defaultmpbase="1540.8" defaultmpadd="33.2" defaultmpmod="0.14" level="76"/>
    <pc-stats pClass="97" className="Cardinal" race="0" str="22" con="27" dex="21" int="41" wit="20" men="39" pAtk="3" pDef="54" mAtk="3" mDef="0" pSpd="300" mSpd="333" acc="28" critical="40" evasion="28" moveSpeed="120" load="62500" x="-90890" y="248027" z="248027" canCraft="false" mColRadius="7.5" mColHeight="22.8" fColRadius="6.5" fColHeight="22.5" items="425 461 6 5588 0" defaulthpbase="3182.7" defaulthpadd="63.08" defaulthpmod="0.37" defaultcpbase="2227.8" defaultcpadd="44.16" defaultcpmod="0.22" defaultmpbase="1540.8" defaultmpadd="33.2" defaultmpmod="0.14" level="76"/>
    <pc-stats pClass="98" className="Hierophant" race="0" str="22" con="27" dex="21" int="41" wit="20" men="39" pAtk="3" pDef="54" mAtk="3" mDef="0" pSpd="300" mSpd="333" acc="28" critical="40" evasion="28" moveSpeed="120" load="62500" x="-90890" y="248027" z="248027" canCraft="false" mColRadius="7.5" mColHeight="22.8" fColRadius="6.5" fColHeight="22.5" items="425 461 6 5588 0" defaulthpbase="3342.0" defaulthpadd="68.06" defaulthpmod="0.37" defaultcpbase="1671.0" defaultcpadd="34.03" defaultcpmod="0.22" defaultmpbase="1540.8" defaultmpadd="33.2" defaultmpmod="0.14" level="76"/>
    <pc-stats pClass="99" className="Eva Templar" race="1" str="36" con="36" dex="35" int="23" wit="14" men="26" pAtk="4" pDef="80" mAtk="4" mDef="0" pSpd="300" mSpd="333" acc="36" critical="46" evasion="36" moveSpeed="125" load="73000" x="45978" y="41196" z="41196" canCraft="false" mColRadius="7.5" mColHeight="24.0" fColRadius="7.5" fColHeight="23.0" items="1147 1146 10 2369 5588" defaulthpbase="3196.0" defaulthpadd="66.4" defaulthpmod="0.37" defaultcpbase="1917.6" defaultcpadd="39.84" defaultcpmod="0.22" defaultmpbase="1155.6" defaultmpadd="24.9" defaultmpmod="0.14" level="76"/>
    <pc-stats pClass="100" className="Sword Muse" race="1" str="36" con="36" dex="35" int="23" wit="14" men="26" pAtk="4" pDef="80" mAtk="4" mDef="0" pSpd="300" mSpd="333" acc="36" critical="46" evasion="36" moveSpeed="125" load="73000" x="45978" y="41196" z="41196" canCraft="false" mColRadius="7.5" mColHeight="24.0" fColRadius="7.5" fColHeight="23.0" items="1147 1146 10 2369 5588" defaulthpbase="3302.2" defaulthpadd="69.72" defaulthpmod="0.37" defaultcpbase="1651.1" defaultcpadd="34.86" defaultcpmod="0.22" defaultmpbase="1155.6" defaultmpadd="24.9" defaultmpmod="0.14" level="76"/>
    <pc-stats pClass="101" className="Wind Rider" race="1" str="36" con="36" dex="35" int="23" wit="14" men="26" pAtk="4" pDef="80" mAtk="4" mDef="0" pSpd="300" mSpd="333" acc="36" critical="46" evasion="36" moveSpeed="125" load="73000" x="45978" y="41196" z="41196" canCraft="false" mColRadius="7.5" mColHeight="24.0" fColRadius="7.5" fColHeight="23.0" items="1147 1146 10 2369 5588" defaulthpbase="2935.8" defaulthpadd="59.76" defaulthpmod="0.37" defaultcpbase="1174.3" defaultcpadd="23.9" defaultcpmod="0.22" defaultmpbase="1155.6" defaultmpadd="24.9" defaultmpmod="0.14" level="76"/>
    <pc-stats pClass="102" className="Moonlight Sentinel" race="1" str="36" con="36" dex="35" int="23" wit="14" men="26" pAtk="4" pDef="80" mAtk="4" mDef="0" pSpd="300" mSpd="333" acc="36" critical="46" evasion="36" moveSpeed="125" load="73000" x="45978" y="41196" z="41196" canCraft="false" mColRadius="7.5" mColHeight="24.0" fColRadius="7.5" fColHeight="23.0" items="1147 1146 10 2369 5588" defaulthpbase="3042.0" defaulthpadd="63.08" defaulthpmod="0.37" defaultcpbase="1521.0" defaultcpadd="31.54" defaultcpmod="0.22" defaultmpbase="1155.6" defaultmpadd="24.9" defaultmpmod="0.14" level="76"/>
    <pc-stats pClass="103" className="Mystic Muse" race="1" str="21" con="25" dex="24" int="37" wit="23" men="40" pAtk="3" pDef="54" mAtk="3" mDef="0" pSpd="300" mSpd="333" acc="30" critical="41" evasion="30" moveSpeed="122" load="62400" x="46182" y="41198" z="41198" canCraft="false" mColRadius="7.5" mColHeight="24.0" fColRadius="7.5" fColHeight="23.0" items="425 461 6 5588 0" defaulthpbase="3013.1" defaulthpadd="61.42" defaulthpmod="0.37" defaultcpbase="1506.5" defaultcpadd="30.71" defaultcpmod="0.22" defaultmpbase="1540.8" defaultmpadd="33.2" defaultmpmod="0.14" level="76"/>
    <pc-stats pClass="104" className="Elemental Master" race="1" str="21" con="25" dex="24" int="37" wit="23" men="40" pAtk="3" pDef="54" mAtk="3" mDef="0" pSpd="300" mSpd="333" acc="30" critical="41" evasion="30" moveSpeed="122" load="62400" x="46182" y="41198" z="41198" canCraft="false" mColRadius="7.5" mColHeight="24.0" fColRadius="7.5" fColHeight="23.0" items="425 461 6 5588 0" defaulthpbase="3119.3" defaulthpadd="64.74" defaulthpmod="0.37" defaultcpbase="1871.5" defaultcpadd="38.84" defaultcpmod="0.22" defaultmpbase="1540.8" defaultmpadd="33.2" defaultmpmod="0.14" level="76"/>
    <pc-stats pClass="105" className="Eva Saint" race="1" str="21" con="25" dex="24" int="37" wit="23" men="40" pAtk="3" pDef="54" mAtk="3" mDef="0" pSpd="300" mSpd="333" acc="30" critical="41" evasion="30" moveSpeed="122" load="62400" x="46182" y="41198" z="41198" canCraft="false" mColRadius="7.5" mColHeight="24.0" fColRadius="7.5" fColHeight="23.0" items="425 461 6 5588 0" defaulthpbase="3422.0" defaulthpadd="69.72" defaulthpmod="0.37" defaultcpbase="1711.0" defaultcpadd="34.86" defaultcpmod="0.22" defaultmpbase="1540.8" defaultmpadd="33.2" defaultmpmod="0.14" level="76"/>
    <pc-stats pClass="106" className="Shillien Templar" race="2" str="41" con="32" dex="34" int="25" wit="12" men="26" pAtk="4" pDef="80" mAtk="4" mDef="0" pSpd="300" mSpd="333" acc="35" critical="45" evasion="35" moveSpeed="122" load="69000" x="28377" y="10916" z="10916" canCraft="false" mColRadius="7.5" mColHeight="24.0" fColRadius="7.0" fColHeight="23.5" items="1147 1146 10 2369 5588" defaulthpbase="3374.0" defaulthpadd="69.72" defaulthpmod="0.37" defaultcpbase="2024.4" defaultcpadd="41.83" defaultcpmod="0.22" defaultmpbase="1155.6" defaultmpadd="24.9" defaultmpmod="0.14" level="76"/>
    <pc-stats pClass="107" className="Spectral Dancer" race="2" str="41" con="32" dex="34" int="25" wit="12" men="26" pAtk="4" pDef="80" mAtk="4" mDef="0" pSpd="300" mSpd="333" acc="35" critical="45" evasion="35" moveSpeed="122" load="69000" x="28377" y="10916" z="10916" canCraft="false" mColRadius="7.5" mColHeight="24.0" fColRadius="7.0" fColHeight="23.5" items="1147 1146 10 2369 5588" defaulthpbase="3533.3" defaulthpadd="74.7" defaulthpmod="0.37" defaultcpbase="1766.6" defaultcpadd="37.35" defaultcpmod="0.22" defaultmpbase="1155.6" defaultmpadd="24.9" defaultmpmod="0.14" level="76"/>
    <pc-stats pClass="108" className="Ghost Hunter" race="2" str="41" con="32" dex="34" int="25" wit="12" men="26" pAtk="4" pDef="80" mAtk="4" mDef="0" pSpd="300" mSpd="333" acc="35" critical="45" evasion="35" moveSpeed="122" load="69000" x="28377" y="10916" z="10916" canCraft="false" mColRadius="7.5" mColHeight="24.0" fColRadius="7.0" fColHeight="23.5" items="1147 1146 10 2369 5588" defaulthpbase="3113.8" defaulthpadd="63.08" defaulthpmod="0.37" defaultcpbase="1245.5" defaultcpadd="25.23" defaultcpmod="0.22" defaultmpbase="1155.6" defaultmpadd="24.9" defaultmpmod="0.14" level="76"/>
    <pc-stats pClass="109" className="Ghost Sentinel" race="2" str="41" con="32" dex="34" int="25" wit="12" men="26" pAtk="4" pDef="80" mAtk="4" mDef="0" pSpd="300" mSpd="333" acc="35" critical="45" evasion="35" moveSpeed="122" load="69000" x="28377" y="10916" z="10916" canCraft="false" mColRadius="7.5" mColHeight="24.0" fColRadius="7.0" fColHeight="23.5" items="1147 1146 10 2369 5588" defaulthpbase="3220.0" defaulthpadd="66.4" defaulthpmod="0.37" defaultcpbase="1610.0" defaultcpadd="33.2" defaultcpmod="0.22" defaultmpbase="1155.6" defaultmpadd="24.9" defaultmpmod="0.14" level="76"/>
    <pc-stats pClass="110" className="Storm Screamer" race="2" str="23" con="24" dex="23" int="44" wit="19" men="37" pAtk="3" pDef="54" mAtk="3" mDef="0" pSpd="300" mSpd="333" acc="29" critical="41" evasion="29" moveSpeed="122" load="61000" x="28295" y="11063" z="11063" canCraft="false" mColRadius="7.5" mColHeight="24.0" fColRadius="7.0" fColHeight="23.5" items="425 461 6 5588 0" defaulthpbase="3039.0" defaulthpadd="61.42" defaulthpmod="0.37" defaultcpbase="1519.5" defaultcpadd="30.71" defaultcpmod="0.22" defaultmpbase="1540.8" defaultmpadd="33.2" defaultmpmod="0.14" level="76"/>
    <pc-stats pClass="111" className="Spectral Master" race="2" str="23" con="24" dex="23" int="44" wit="19" men="37" pAtk="3" pDef="54" mAtk="3" mDef="0" pSpd="300" mSpd="333" acc="29" critical="41" evasion="29" moveSpeed="122" load="61000" x="28295" y="11063" z="11063" canCraft="false" mColRadius="7.5" mColHeight="24.0" fColRadius="7.0" fColHeight="23.5" items="425 461 6 5588 0" defaulthpbase="3198.3" defaulthpadd="66.4" defaulthpmod="0.37" defaultcpbase="1918.9" defaultcpadd="39.84" defaultcpmod="0.22" defaultmpbase="1540.8" defaultmpadd="33.2" defaultmpmod="0.14" level="76"/>
    <pc-stats pClass="112" className="Shillen Saint" race="2" str="23" con="24" dex="23" int="44" wit="19" men="37" pAtk="3" pDef="54" mAtk="3" mDef="0" pSpd="300" mSpd="333" acc="29" critical="41" evasion="29" moveSpeed="122" load="61000" x="28295" y="11063" z="11063" canCraft="false" mColRadius="7.5" mColHeight="24.0" fColRadius="7.0" fColHeight="23.5" items="425 461 6 5588 0" defaulthpbase="3447.9" defaulthpadd="69.72" defaulthpmod="0.37" defaultcpbase="1723.9" defaultcpadd="34.86" defaultcpmod="0.22" defaultmpbase="1540.8" defaultmpadd="33.2" defaultmpmod="0.14" level="76"/>
    <pc-stats pClass="113" className="Titan" race="3" str="40" con="47" dex="26" int="18" wit="12" men="27" pAtk="4" pDef="80" mAtk="4" mDef="0" pSpd="300" mSpd="333" acc="31" critical="42" evasion="31" moveSpeed="117" load="87000" x="-56693" y="-113610" z="-113610" canCraft="false" mColRadius="11.0" mColHeight="28.0" fColRadius="7.0" fColHeight="27.0" items="1147 1146 2368 2369 5588" defaulthpbase="3447.2" defaulthpadd="72.94" defaulthpmod="0.37" defaultcpbase="2413.0" defaultcpadd="51.03" defaultcpmod="0.22" defaultmpbase="1155.6" defaultmpadd="24.8" defaultmpmod="0.14" level="76"/>
    <pc-stats pClass="114" className="Grand Khauatari" race="3" str="40" con="47" dex="26" int="18" wit="12" men="27" pAtk="4" pDef="80" mAtk="4" mDef="0" pSpd="300" mSpd="333" acc="31" critical="42" evasion="31" moveSpeed="117" load="87000" x="-56693" y="-113610" z="-113610" canCraft="false" mColRadius="11.0" mColHeight="28.0" fColRadius="7.0" fColHeight="27.0" items="1147 1146 2368 2369 5588" defaulthpbase="3293.2" defaulthpadd="69.62" defaulthpmod="0.37" defaultcpbase="1646.6" defaultcpadd="34.76" defaultcpmod="0.22" defaultmpbase="1155.6" defaultmpadd="24.8" defaultmpmod="0.14" level="76"/>
    <pc-stats pClass="115" className="Dominator" race="3" str="27" con="31" dex="24" int="31" wit="15" men="42" pAtk="3" pDef="54" mAtk="3" mDef="0" pSpd="300" mSpd="333" acc="30" critical="41" evasion="30" moveSpeed="121" load="68000" x="-56682" y="-113730" z="-113730" canCraft="false" mColRadius="7.0" mColHeight="27.5" fColRadius="8.0" fColHeight="25.5" items="425 461 2368 5588 0" defaulthpbase="3359.9" defaulthpadd="67.96" defaulthpmod="0.37" defaultcpbase="2687.9" defaultcpadd="54.35" defaultcpmod="0.22" defaultmpbase="1540.8" defaultmpadd="33.1" defaultmpmod="0.14" level="76"/>
    <pc-stats pClass="116" className="Doomcryer" race="3" str="27" con="31" dex="24" int="31" wit="15" men="42" pAtk="3" pDef="54" mAtk="3" mDef="0" pSpd="300" mSpd="333" acc="30" critical="41" evasion="30" moveSpeed="121" load="68000" x="-56682" y="-113730" z="-113730" canCraft="false" mColRadius="7.0" mColHeight="27.5" fColRadius="8.0" fColHeight="25.5" items="425 461 2368 5588 0" defaulthpbase="3359.9" defaulthpadd="67.96" defaulthpmod="0.37" defaultcpbase="1679.9" defaultcpadd="33.93" defaultcpmod="0.22" defaultmpbase="1540.8" defaultmpadd="33.1" defaultmpmod="0.14" level="76"/>
    <pc-stats pClass="117" className="Fortune Seeker" race="4" str="39" con="45" dex="29" int="20" wit="10" men="27" pAtk="4" pDef="80" mAtk="4" mDef="0" pSpd="300" mSpd="333" acc="33" critical="43" evasion="33" moveSpeed="115" load="83000" x="108512" y="-174026" z="-174026" canCraft="true" mColRadius="9.0" mColHeight="18.0" fColRadius="5.0" fColHeight="19.0" items="1147 1146 10 2370 5588" defaulthpbase="3447.2" defaulthpadd="72.94" defaulthpmod="0.37" defaultcpbase="2413.0" defaultcpadd="51.03" defaultcpmod="0.22" defaultmpbase="1155.6" defaultmpadd="24.8" defaultmpmod="0.14" level="76"/>
    <pc-stats pClass="118" className="Maestro" race="4" str="39" con="45" dex="29" int="20" wit="10" men="27" pAtk="4" pDef="80" mAtk="4" mDef="0" pSpd="300" mSpd="333" acc="33" critical="43" evasion="33" moveSpeed="115" load="83000" x="108512" y="-174026" z="-174026" canCraft="true" mColRadius="9.0" mColHeight="18.0" fColRadius="5.0" fColHeight="19.0" items="1147 1146 10 2370 5588" defaulthpbase="3293.2" defaulthpadd="69.62" defaulthpmod="0.37" defaultcpbase="2634.5" defaultcpadd="55.68" defaultcpmod="0.22" defaultmpbase="1155.6" defaultmpadd="24.8" defaultmpmod="0.14" level="76"/>
</data>
